onnx2torch/__init__.py
onnx2torch/version.py
onnx2torch/cli/__init__.py
onnx2torch/cli/_main.py
onnx2torch/core/__init__.py
onnx2torch/core/comparator.py
onnx2torch/core/parser.py
onnx2torch/core/pytorch_layers/Inspector_module.py
onnx2torch/core/pytorch_layers/__init__.py
onnx2torch/core/pytorch_layers/batchnorm.py
onnx2torch/core/pytorch_layers/conv.py
onnx2torch/core/pytorch_layers/embedding_layer.py
onnx2torch/core/pytorch_layers/instancenorm.py
onnx2torch/core/pytorch_layers/layernorm.py
onnx2torch/core/pytorch_layers/linear.py
onnx2torch/core/pytorch_layers/observer.py
onnx2torch/core/pytorch_layers/pad_layer.py
onnx2torch/core/pytorch_layers/pool.py
onnx2torch/core/pytorch_layers/slice_layer.py
onnx2torch/core/pytorch_layers/torch_layer.py
onnx2torch/core/pytorch_layers/utils.py
onnx2torch/onnx_graphsurgeon/__init__.py
onnx2torch/onnx_graphsurgeon/exporters/__init__.py
onnx2torch/onnx_graphsurgeon/exporters/base_exporter.py
onnx2torch/onnx_graphsurgeon/exporters/onnx_exporter.py
onnx2torch/onnx_graphsurgeon/importers/__init__.py
onnx2torch/onnx_graphsurgeon/importers/base_importer.py
onnx2torch/onnx_graphsurgeon/importers/onnx_importer.py
onnx2torch/onnx_graphsurgeon/ir/__init__.py
onnx2torch/onnx_graphsurgeon/ir/graph.py
onnx2torch/onnx_graphsurgeon/ir/node.py
onnx2torch/onnx_graphsurgeon/ir/tensor.py
onnx2torch/onnx_graphsurgeon/logger/__init__.py
onnx2torch/onnx_graphsurgeon/logger/logger.py
onnx2torch/onnx_graphsurgeon/util/__init__.py
onnx2torch/onnx_graphsurgeon/util/exception.py
onnx2torch/onnx_graphsurgeon/util/misc.py
onnx2torch/utils/__init__.py
onnx2torch/utils/utils.py
o2t-0.1.0.dist-info/LICENSE
o2t-0.1.0.dist-info/METADATA
o2t-0.1.0.dist-info/WHEEL
o2t-0.1.0.dist-info/entry_points.txt
o2t-0.1.0.dist-info/top_level.txt
o2t-0.1.0.dist-info/zip-safe
o2t-0.1.0.dist-info/RECORD
